{
  "racers": [
    null,
    {
      "#": 1,
      "SailNo": 3670,
      "Class": "Merlin Rocket",
      "PY": 980,
      "Fleet": "G",
      "Helm": "Mark McKeever",
      "Crew": "Gracie McKeever",
      "Laps": 2,
      "Time": "40:44",
      "Corrected": 2494,
      "&nbsp;": "",
      "Pts": 1
    },
    {
      "#": 2,
      "SailNo": 3700,
      "Class": "Merlin Rocket",
      "PY": 980,
      "Fleet": "G",
      "Helm": "Rob Kennaugh",
      "Crew": "George Bender",
      "Laps": 2,
      "Time": "40:57",
      "Corrected": 2507,
      "&nbsp;": "",
      "Pts": 2
    },
    {
      "#": 3,
      "SailNo": 1274,
      "Class": "Phantom",
      "PY": 1004,
      "Fleet": "B",
      "Helm": "Evan Base",
      "Crew": "",
      "Laps": 2,
      "Time": "42:49",
      "Corrected": 2559,
      "&nbsp;": "",
      "Pts": 3
    },
    {
      "#": 4,
      "SailNo": 13204,
      "Class": "GP14",
      "PY": 1130,
      "Fleet": "S",
      "Helm": "Mike Homer",
      "Crew": "Alex Homer",
      "Laps": 2,
      "Time": "48:23",
      "Corrected": 2569,
      "&nbsp;": "",
      "Pts": 4
    },
    {
      "#": 5,
      "SailNo": 165490,
      "Class": "ILCA 7",
      "PY": 1100,
      "Fleet": "S",
      "Helm": "Dean Jung",
      "Crew": "",
      "Laps": 2,
      "Time": "47:14",
      "Corrected": 2576,
      "&nbsp;": "",
      "Pts": 5
    },
    {
      "#": 6,
      "SailNo": 201354,
      "Class": "ILCA 7",
      "PY": 1100,
      "Fleet": "B",
      "Helm": "Phil Deeley",
      "Crew": "",
      "Laps": 2,
      "Time": "48:21",
      "Corrected": 2637,
      "&nbsp;": "",
      "Pts": 6
    },
    {
      "#": 7,
      "SailNo": 20937,
      "Class": "Enterprise",
      "PY": 1122,
      "Fleet": "G",
      "Helm": "Paul Young",
      "Crew": "Jan Kimber",
      "Laps": 2,
      "Time": "50:14",
      "Corrected": 2686,
      "&nbsp;": "",
      "Pts": 7
    },
    {
      "#": 8,
      "SailNo": 172283,
      "Class": "ILCA 7",
      "PY": 1100,
      "Fleet": "B",
      "Helm": "Rob Thorp",
      "Crew": "",
      "Laps": 2,
      "Time": "49:56",
      "Corrected": 2724,
      "&nbsp;": "",
      "Pts": 8
    },
    {
      "#": 9,
      "SailNo": 3530,
      "Class": "Merlin Rocket",
      "PY": 980,
      "Fleet": "B",
      "Helm": "Mike Colles",
      "Crew": "Lauren Morgan",
      "Laps": 2,
      "Time": "47:18",
      "Corrected": 2896,
      "&nbsp;": "",
      "Pts": 9
    },
    {
      "#": 10,
      "SailNo": 1904,
      "Class": "Streaker",
      "PY": 1128,
      "Fleet": "S",
      "Helm": "Chris Skelcher",
      "Crew": "",
      "Laps": 2,
      "Time": "56:36",
      "Corrected": 3011,
      "&nbsp;": "",
      "Pts": 10
    },
    {
      "#": 11,
      "SailNo": 13789,
      "Class": "GP14",
      "PY": 1130,
      "Fleet": "B",
      "Helm": "Douglas Bridger",
      "Crew": "",
      "Laps": 2,
      "Time": "57:03",
      "Corrected": 3029,
      "&nbsp;": "",
      "Pts": 11
    },
    {
      "#": 12,
      "SailNo": 4366,
      "Class": "Solo",
      "PY": 1142,
      "Fleet": "B",
      "Helm": "Stuart Jones",
      "Crew": "",
      "Laps": 2,
      "Time": "58:07",
      "Corrected": 3053,
      "&nbsp;": "",
      "Pts": 12
    }
  ]
}
