{
  "racers": [
    null,
    {
      "#": 1,
      "SailNo": 1274,
      "Class": "Phantom",
      "PY": 1004,
      "Fleet": "B",
      "Helm": "Evan Base",
      "Crew": "",
      "Laps": 4,
      "Time": "61:19",
      "Corrected": 3664,
      "&nbsp;": "",
      "Pts": 1
    },
    {
      "#": 2,
      "SailNo": 4315,
      "Class": "Solo",
      "PY": 1142,
      "Fleet": "G",
      "Helm": "Chris Martin",
      "Crew": "",
      "Laps": 3,
      "Time": "52:48",
      "Corrected": 3699,
      "&nbsp;": "",
      "Pts": 2
    },
    {
      "#": 3,
      "SailNo": 414,
      "Class": "RS300",
      "PY": 970,
      "Fleet": "G",
      "Helm": "Rob Kennaugh",
      "Crew": "",
      "Laps": 4,
      "Time": "61:03",
      "Corrected": 3776,
      "&nbsp;": "",
      "Pts": 3
    },
    {
      "#": 4,
      "SailNo": 22901,
      "Class": "Enterprise",
      "PY": 1122,
      "Fleet": "G",
      "Helm": "Paul Young",
      "Crew": "Jan Kimber",
      "Laps": 3,
      "Time": "54:43",
      "Corrected": 3901,
      "&nbsp;": "",
      "Pts": 4
    },
    {
      "#": 5,
      "SailNo": 1436,
      "Class": "Phantom",
      "PY": 1004,
      "Fleet": "S",
      "Helm": "Jan Holland",
      "Crew": "",
      "Laps": 3,
      "Time": "49:56",
      "Corrected": 3979,
      "&nbsp;": "",
      "Pts": 5
    },
    {
      "#": 6,
      "SailNo": 150112,
      "Class": "ILCA 7",
      "PY": 1100,
      "Fleet": "B",
      "Helm": "Matthew McLullich",
      "Crew": "",
      "Laps": 3,
      "Time": "54:53",
      "Corrected": 3992,
      "&nbsp;": "",
      "Pts": 6
    },
    {
      "#": 7,
      "SailNo": 201354,
      "Class": "ILCA 7",
      "PY": 1100,
      "Fleet": "B",
      "Helm": "Phil Deeley",
      "Crew": "",
      "Laps": 3,
      "Time": "55:28",
      "Corrected": 4034,
      "&nbsp;": "",
      "Pts": 7
    },
    {
      "#": 8,
      "SailNo": 3794,
      "Class": "Merlin Rocket",
      "PY": 980,
      "Fleet": "S",
      "Helm": "Julian Harms",
      "Crew": "George Bender",
      "Laps": 3,
      "Time": "49:59",
      "Corrected": 4080,
      "&nbsp;": "",
      "Pts": 8
    },
    {
      "#": 9,
      "SailNo": 4146,
      "Class": "Solo",
      "PY": 1142,
      "Fleet": "B",
      "Helm": "Oliver Mason",
      "Crew": "",
      "Laps": 3,
      "Time": "58:27",
      "Corrected": 4095,
      "&nbsp;": "",
      "Pts": 9
    },
    {
      "#": 10,
      "SailNo": 77637,
      "Class": "ILCA 7",
      "PY": 1100,
      "Fleet": "B",
      "Helm": "Jason Larner",
      "Crew": "",
      "Laps": 3,
      "Time": "57:14",
      "Corrected": 4162,
      "&nbsp;": "",
      "Pts": 10
    },
    {
      "#": 11,
      "SailNo": 4348,
      "Class": "Solo",
      "PY": 1142,
      "Fleet": "S",
      "Helm": "Lawrence Bowbanks",
      "Crew": "",
      "Laps": 3,
      "Time": "59:34",
      "Corrected": 4173,
      "&nbsp;": "",
      "Pts": 11
    },
    {
      "#": 12,
      "SailNo": 3530,
      "Class": "Merlin Rocket",
      "PY": 980,
      "Fleet": "B",
      "Helm": "Mike Colles",
      "Crew": "Melanie Beavan",
      "Laps": 3,
      "Time": "53:08",
      "Corrected": 4337,
      "&nbsp;": "",
      "Pts": 12
    }
  ]
}
